{
  "id": "quechoa9-live",
  "name": "QueCho9 — Trực tiếp bóng đá",
  "url": "https://quechoa9.live/",
  "description": "Cập nhật lúc 04/04/2026 22:03 ICT (ICT)",
  "disable_ads": true,
  "color": "#0f3460",
  "grid_number": 3,
  "image": {
    "type": "cover",
    "url": "https://quechoa9.live/favicon.ico"
  },
  "groups": [
    {
      "id": "tam-diem",
      "name": "🔥 Trận đấu tâm điểm",
      "image": null,
      "channels": [
        {
          "id": "qc-1-sc-freiburg-vs-bayern-m",
          "name": "SC Freiburg 2-0 Bayern München  🔴",
          "type": "single",
          "display": "thumbnail-only",
          "enable_detail": false,
          "image": {
            "padding": 1,
            "background_color": "#ececec",
            "display": "contain",
            "url": "https://quechoa9.live/images/cards/card-bg.jpg",
            "width": 1600,
            "height": 1200
          },
          "labels": [
            {
              "text": "● Live",
              "color": "#E73131",
              "text_color": "#ffffff",
              "position": "top-left"
            },
            {
              "text": "🎙 KHOAI TÂY",
              "position": "top-right",
              "color": "#00601f",
              "text_color": "#ffffff"
            },
            {
              "text": "⚽ 2-0",
              "position": "bottom-right",
              "color": "#E73131",
              "text_color": "#ffffff"
            }
          ],
          "sources": [
            {
              "id": "qc-1-sc-freiburg-vs-bayern-m-src",
              "name": "QueCho9 Live",
              "contents": [
                {
                  "id": "qc-1-sc-freiburg-vs-bayern-m-ct",
                  "name": "SC Freiburg 2-0 Bayern München  🔴",
                  "streams": [
                    {
                      "id": "qc-1-sc-freiburg-vs-bayern-m-st",
                      "name": "Trực tiếp · Live13:30|04.04BundesligaSC Freiburg2:0Bayern MünchenKKHOAI TÂYĐặt cược",
                      "stream_links": [
                        {
                          "id": "qc-1-sc-freiburg-vs-bayern-m-lnk-0",
                          "name": "🎙 KHOAI TÂY — Auto",
                          "type": "hls",
                          "default": true,
                          "url": "https://ahghndtkyqmm-pull.bpmedialive.com/quechoa/blv_2.m3u8",
                          "request_headers": [
                            {
                              "key": "Referer",
                              "value": "https://quechoa9.live/truc-tiep/sc-freiburg-vs-bayern-munchen-ebt-04-04-2026"
                            },
                            {
                              "key": "User-Agent",
                              "value": "Mozilla/5.0 (Windows NT 10.0; Win64; x64) AppleWebKit/537.36 (KHTML, like Gecko) Chrome/124.0.0.0 Safari/537.36"
                            }
                          ]
                        },
                        {
                          "id": "qc-1-sc-freiburg-vs-bayern-m-lnk-1",
                          "name": "🎙 KHOAI TÂY — HD",
                          "type": "hls",
                          "default": false,
                          "url": "https://ahghndtkyqmm-pull.bpmedialive.com/quechoa/blv_2_hd.m3u8",
                          "request_headers": [
                            {
                              "key": "Referer",
                              "value": "https://quechoa9.live/truc-tiep/sc-freiburg-vs-bayern-munchen-ebt-04-04-2026"
                            },
                            {
                              "key": "User-Agent",
                              "value": "Mozilla/5.0 (Windows NT 10.0; Win64; x64) AppleWebKit/537.36 (KHTML, like Gecko) Chrome/124.0.0.0 Safari/537.36"
                            }
                          ]
                        },
                        {
                          "id": "qc-1-sc-freiburg-vs-bayern-m-lnk-2",
                          "name": "🎙 KHOAI TÂY — SD",
                          "type": "hls",
                          "default": false,
                          "url": "https://ahghndtkyqmm-pull.bpmedialive.com/quechoa/blv_2_sd.m3u8",
                          "request_headers": [
                            {
                              "key": "Referer",
                              "value": "https://quechoa9.live/truc-tiep/sc-freiburg-vs-bayern-munchen-ebt-04-04-2026"
                            },
                            {
                              "key": "User-Agent",
                              "value": "Mozilla/5.0 (Windows NT 10.0; Win64; x64) AppleWebKit/537.36 (KHTML, like Gecko) Chrome/124.0.0.0 Safari/537.36"
                            }
                          ]
                        }
                      ]
                    }
                  ]
                }
              ]
            }
          ]
        },
        {
          "id": "qc-2-bayer-leverkusen-vs-vfl",
          "name": "Bayer Leverkusen 4-3 VfL Wolfsburg  🔴",
          "type": "single",
          "display": "thumbnail-only",
          "enable_detail": false,
          "image": {
            "padding": 1,
            "background_color": "#ececec",
            "display": "contain",
            "url": "https://quechoa9.live/images/cards/card-bg.jpg",
            "width": 1600,
            "height": 1200
          },
          "labels": [
            {
              "text": "● Live",
              "color": "#E73131",
              "text_color": "#ffffff",
              "position": "top-left"
            },
            {
              "text": "🎙 NEM CHUA",
              "position": "top-right",
              "color": "#00601f",
              "text_color": "#ffffff"
            },
            {
              "text": "⚽ 4-3",
              "position": "bottom-right",
              "color": "#E73131",
              "text_color": "#ffffff"
            }
          ],
          "sources": [
            {
              "id": "qc-2-bayer-leverkusen-vs-vfl-src",
              "name": "QueCho9 Live",
              "contents": [
                {
                  "id": "qc-2-bayer-leverkusen-vs-vfl-ct",
                  "name": "Bayer Leverkusen 4-3 VfL Wolfsburg  🔴",
                  "streams": [
                    {
                      "id": "qc-2-bayer-leverkusen-vs-vfl-st",
                      "name": "Trực tiếp · Live13:30|04.04BundesligaBayer Leverkusen4:3VfL WolfsburgNNEM CHUAĐặt cược",
                      "stream_links": [
                        {
                          "id": "qc-2-bayer-leverkusen-vs-vfl-lnk-0",
                          "name": "🎙 NEM CHUA — Full HD",
                          "type": "hls",
                          "default": true,
                          "url": "https://ahghndtkyqmm-pull.bpmedialive.com/quechoa/blv_banhmuot_full-hd.m3u8",
                          "request_headers": [
                            {
                              "key": "Referer",
                              "value": "https://quechoa9.live/truc-tiep/bayer-leverkusen-vs-vfl-wolfsburg-qeh-04-04-2026"
                            },
                            {
                              "key": "User-Agent",
                              "value": "Mozilla/5.0 (Windows NT 10.0; Win64; x64) AppleWebKit/537.36 (KHTML, like Gecko) Chrome/124.0.0.0 Safari/537.36"
                            }
                          ]
                        },
                        {
                          "id": "qc-2-bayer-leverkusen-vs-vfl-lnk-1",
                          "name": "🎙 NEM CHUA — HD",
                          "type": "hls",
                          "default": false,
                          "url": "https://ahghndtkyqmm-pull.bpmedialive.com/quechoa/blv_banhmuot_hd.m3u8",
                          "request_headers": [
                            {
                              "key": "Referer",
                              "value": "https://quechoa9.live/truc-tiep/bayer-leverkusen-vs-vfl-wolfsburg-qeh-04-04-2026"
                            },
                            {
                              "key": "User-Agent",
                              "value": "Mozilla/5.0 (Windows NT 10.0; Win64; x64) AppleWebKit/537.36 (KHTML, like Gecko) Chrome/124.0.0.0 Safari/537.36"
                            }
                          ]
                        },
                        {
                          "id": "qc-2-bayer-leverkusen-vs-vfl-lnk-2",
                          "name": "🎙 NEM CHUA — SD",
                          "type": "hls",
                          "default": false,
                          "url": "https://ahghndtkyqmm-pull.bpmedialive.com/quechoa/blv_banhmuot_sd.m3u8",
                          "request_headers": [
                            {
                              "key": "Referer",
                              "value": "https://quechoa9.live/truc-tiep/bayer-leverkusen-vs-vfl-wolfsburg-qeh-04-04-2026"
                            },
                            {
                              "key": "User-Agent",
                              "value": "Mozilla/5.0 (Windows NT 10.0; Win64; x64) AppleWebKit/537.36 (KHTML, like Gecko) Chrome/124.0.0.0 Safari/537.36"
                            }
                          ]
                        }
                      ]
                    }
                  ]
                }
              ]
            }
          ]
        },
        {
          "id": "qc-3-mallorca-vs-real-madrid",
          "name": "Mallorca 1-0 Real Madrid  🔴",
          "type": "single",
          "display": "thumbnail-only",
          "enable_detail": false,
          "image": {
            "padding": 1,
            "background_color": "#ececec",
            "display": "contain",
            "url": "https://quechoa9.live/images/cards/card-bg.jpg",
            "width": 1600,
            "height": 1200
          },
          "labels": [
            {
              "text": "● Live",
              "color": "#E73131",
              "text_color": "#ffffff",
              "position": "top-left"
            },
            {
              "text": "🎙 3 BLV",
              "position": "top-right",
              "color": "#00601f",
              "text_color": "#ffffff"
            },
            {
              "text": "⚽ 1-0",
              "position": "bottom-right",
              "color": "#E73131",
              "text_color": "#ffffff"
            }
          ],
          "sources": [
            {
              "id": "qc-3-mallorca-vs-real-madrid-src",
              "name": "QueCho9 Live",
              "contents": [
                {
                  "id": "qc-3-mallorca-vs-real-madrid-ct",
                  "name": "Mallorca 1-0 Real Madrid  🔴",
                  "streams": [
                    {
                      "id": "qc-3-mallorca-vs-real-madrid-st",
                      "name": "Trực tiếp · Live14:15|04.04La LigaMallorca1:0Real MadridDDƯA HẤUĐặt cược · 3 BLV",
                      "stream_links": [
                        {
                          "id": "qc-3-mallorca-vs-real-madrid-lnk-0",
                          "name": "🎙 DƯA HẤU — Full HD",
                          "type": "hls",
                          "default": true,
                          "url": "https://ahghndtkyqmm-pull.bpmedialive.com/quechoa/blv_supluon_full-hd.m3u8",
                          "request_headers": [
                            {
                              "key": "Referer",
                              "value": "https://quechoa9.live/truc-tiep/mallorca-vs-real-madrid-ehr-04-04-2026"
                            },
                            {
                              "key": "User-Agent",
                              "value": "Mozilla/5.0 (Windows NT 10.0; Win64; x64) AppleWebKit/537.36 (KHTML, like Gecko) Chrome/124.0.0.0 Safari/537.36"
                            }
                          ]
                        },
                        {
                          "id": "qc-3-mallorca-vs-real-madrid-lnk-1",
                          "name": "🎙 DƯA HẤU — HD",
                          "type": "hls",
                          "default": false,
                          "url": "https://ahghndtkyqmm-pull.bpmedialive.com/quechoa/blv_supluon_hd.m3u8",
                          "request_headers": [
                            {
                              "key": "Referer",
                              "value": "https://quechoa9.live/truc-tiep/mallorca-vs-real-madrid-ehr-04-04-2026"
                            },
                            {
                              "key": "User-Agent",
                              "value": "Mozilla/5.0 (Windows NT 10.0; Win64; x64) AppleWebKit/537.36 (KHTML, like Gecko) Chrome/124.0.0.0 Safari/537.36"
                            }
                          ]
                        },
                        {
                          "id": "qc-3-mallorca-vs-real-madrid-lnk-2",
                          "name": "🎙 DƯA HẤU — SD",
                          "type": "hls",
                          "default": false,
                          "url": "https://ahghndtkyqmm-pull.bpmedialive.com/quechoa/blv_supluon_sd.m3u8",
                          "request_headers": [
                            {
                              "key": "Referer",
                              "value": "https://quechoa9.live/truc-tiep/mallorca-vs-real-madrid-ehr-04-04-2026"
                            },
                            {
                              "key": "User-Agent",
                              "value": "Mozilla/5.0 (Windows NT 10.0; Win64; x64) AppleWebKit/537.36 (KHTML, like Gecko) Chrome/124.0.0.0 Safari/537.36"
                            }
                          ]
                        },
                        {
                          "id": "qc-3-mallorca-vs-real-madrid-lnk-3",
                          "name": "🎙 KHU MẤN",
                          "type": "hls",
                          "default": false,
                          "url": "https://ahghndtkyqmm-pull.bpmedialive.com/quechoa/blv_lachanh_full-hd.m3u8",
                          "request_headers": [
                            {
                              "key": "Referer",
                              "value": "https://quechoa9.live/truc-tiep/mallorca-vs-real-madrid-fbk-04-04-2026"
                            },
                            {
                              "key": "User-Agent",
                              "value": "Mozilla/5.0 (Windows NT 10.0; Win64; x64) AppleWebKit/537.36 (KHTML, like Gecko) Chrome/124.0.0.0 Safari/537.36"
                            }
                          ]
                        },
                        {
                          "id": "qc-3-mallorca-vs-real-madrid-lnk-4",
                          "name": "🎙 PUMA — Full HD",
                          "type": "hls",
                          "default": false,
                          "url": "https://ahghndtkyqmm-pull.bpmedialive.com/quechoa/blv_banhda_full-hd.m3u8",
                          "request_headers": [
                            {
                              "key": "Referer",
                              "value": "https://quechoa9.live/truc-tiep/mallorca-vs-real-madrid-ffz-04-04-2026"
                            },
                            {
                              "key": "User-Agent",
                              "value": "Mozilla/5.0 (Windows NT 10.0; Win64; x64) AppleWebKit/537.36 (KHTML, like Gecko) Chrome/124.0.0.0 Safari/537.36"
                            }
                          ]
                        },
                        {
                          "id": "qc-3-mallorca-vs-real-madrid-lnk-5",
                          "name": "🎙 PUMA — HD",
                          "type": "hls",
                          "default": false,
                          "url": "https://ahghndtkyqmm-pull.bpmedialive.com/quechoa/blv_banhda_hd.m3u8",
                          "request_headers": [
                            {
                              "key": "Referer",
                              "value": "https://quechoa9.live/truc-tiep/mallorca-vs-real-madrid-ffz-04-04-2026"
                            },
                            {
                              "key": "User-Agent",
                              "value": "Mozilla/5.0 (Windows NT 10.0; Win64; x64) AppleWebKit/537.36 (KHTML, like Gecko) Chrome/124.0.0.0 Safari/537.36"
                            }
                          ]
                        },
                        {
                          "id": "qc-3-mallorca-vs-real-madrid-lnk-6",
                          "name": "🎙 PUMA — SD",
                          "type": "hls",
                          "default": false,
                          "url": "https://ahghndtkyqmm-pull.bpmedialive.com/quechoa/blv_banhda_sd.m3u8",
                          "request_headers": [
                            {
                              "key": "Referer",
                              "value": "https://quechoa9.live/truc-tiep/mallorca-vs-real-madrid-ffz-04-04-2026"
                            },
                            {
                              "key": "User-Agent",
                              "value": "Mozilla/5.0 (Windows NT 10.0; Win64; x64) AppleWebKit/537.36 (KHTML, like Gecko) Chrome/124.0.0.0 Safari/537.36"
                            }
                          ]
                        }
                      ]
                    }
                  ]
                }
              ]
            }
          ]
        },
        {
          "id": "qc-4-d-ng-qu-c-ho-ng-vs-piju",
          "name": "Dương Quốc Hoàng vs Pijus Labutis  🕐 16:00 | 04/04",
          "type": "single",
          "display": "thumbnail-only",
          "enable_detail": false,
          "image": {
            "padding": 1,
            "background_color": "#ececec",
            "display": "contain",
            "url": "https://image.quechoacdn.live/cdn-cgi/image/width=3840,format=auto/https://storage.quechoa2.live/backgrounds/sports/match-card/1767467876769-card-bida.png",
            "width": 1600,
            "height": 1200
          },
          "labels": [
            {
              "text": "🕐 Sắp diễn ra",
              "color": "#d54f1a",
              "text_color": "#ffffff",
              "position": "top-left"
            },
            {
              "text": "🎙 PUMA",
              "position": "top-right",
              "color": "#00601f",
              "text_color": "#ffffff"
            },
            {
              "text": "🕐 16:00 | 04/04",
              "position": "bottom-left",
              "color": "#1a5fa8",
              "text_color": "#ffffff"
            }
          ],
          "sources": [
            {
              "id": "qc-4-d-ng-qu-c-ho-ng-vs-piju-src",
              "name": "QueCho9 Live",
              "contents": [
                {
                  "id": "qc-4-d-ng-qu-c-ho-ng-vs-piju-ct",
                  "name": "Dương Quốc Hoàng vs Pijus Labutis  🕐 16:00 | 04/04",
                  "streams": [
                    {
                      "id": "qc-4-d-ng-qu-c-ho-ng-vs-piju-st",
                      "name": "Trực tiếp · Sắp diễn ra16:00|04.048 BALL WORLD CHAMPIONSHIPDương Quốc HoàngVSPijus LabutisPPUMAĐặt cược",
                      "stream_links": [
                        {
                          "id": "qc-4-d-ng-qu-c-ho-ng-vs-piju-lnk-0",
                          "name": "🎙 PUMA — Full HD",
                          "type": "hls",
                          "default": true,
                          "url": "https://ahghndtkyqmm-pull.bpmedialive.com/quechoa/blv_banhda_full-hd.m3u8",
                          "request_headers": [
                            {
                              "key": "Referer",
                              "value": "https://quechoa9.live/truc-tiep/duong-quoc-hoang-vs-pijus-labutis-jmh-04-04-2026"
                            },
                            {
                              "key": "User-Agent",
                              "value": "Mozilla/5.0 (Windows NT 10.0; Win64; x64) AppleWebKit/537.36 (KHTML, like Gecko) Chrome/124.0.0.0 Safari/537.36"
                            }
                          ]
                        },
                        {
                          "id": "qc-4-d-ng-qu-c-ho-ng-vs-piju-lnk-1",
                          "name": "🎙 PUMA — HD",
                          "type": "hls",
                          "default": false,
                          "url": "https://ahghndtkyqmm-pull.bpmedialive.com/quechoa/blv_banhda_hd.m3u8",
                          "request_headers": [
                            {
                              "key": "Referer",
                              "value": "https://quechoa9.live/truc-tiep/duong-quoc-hoang-vs-pijus-labutis-jmh-04-04-2026"
                            },
                            {
                              "key": "User-Agent",
                              "value": "Mozilla/5.0 (Windows NT 10.0; Win64; x64) AppleWebKit/537.36 (KHTML, like Gecko) Chrome/124.0.0.0 Safari/537.36"
                            }
                          ]
                        },
                        {
                          "id": "qc-4-d-ng-qu-c-ho-ng-vs-piju-lnk-2",
                          "name": "🎙 PUMA — SD",
                          "type": "hls",
                          "default": false,
                          "url": "https://ahghndtkyqmm-pull.bpmedialive.com/quechoa/blv_banhda_sd.m3u8",
                          "request_headers": [
                            {
                              "key": "Referer",
                              "value": "https://quechoa9.live/truc-tiep/duong-quoc-hoang-vs-pijus-labutis-jmh-04-04-2026"
                            },
                            {
                              "key": "User-Agent",
                              "value": "Mozilla/5.0 (Windows NT 10.0; Win64; x64) AppleWebKit/537.36 (KHTML, like Gecko) Chrome/124.0.0.0 Safari/537.36"
                            }
                          ]
                        }
                      ]
                    }
                  ]
                }
              ]
            }
          ]
        },
        {
          "id": "qc-5-chelsea-vs-port-vale",
          "name": "Chelsea vs Port Vale  🕐 16:15 | 04/04",
          "type": "single",
          "display": "thumbnail-only",
          "enable_detail": false,
          "image": {
            "padding": 1,
            "background_color": "#ececec",
            "display": "contain",
            "url": "https://quechoa9.live/images/cards/card-bg.jpg",
            "width": 1600,
            "height": 1200
          },
          "labels": [
            {
              "text": "🕐 Sắp diễn ra",
              "color": "#d54f1a",
              "text_color": "#ffffff",
              "position": "top-left"
            },
            {
              "text": "🎙 2 BLV",
              "position": "top-right",
              "color": "#00601f",
              "text_color": "#ffffff"
            },
            {
              "text": "🕐 16:15 | 04/04",
              "position": "bottom-left",
              "color": "#1a5fa8",
              "text_color": "#ffffff"
            }
          ],
          "sources": [
            {
              "id": "qc-5-chelsea-vs-port-vale-src",
              "name": "QueCho9 Live",
              "contents": [
                {
                  "id": "qc-5-chelsea-vs-port-vale-ct",
                  "name": "Chelsea vs Port Vale  🕐 16:15 | 04/04",
                  "streams": [
                    {
                      "id": "qc-5-chelsea-vs-port-vale-st",
                      "name": "Trực tiếp · Sắp diễn ra16:15|04.04FA CupChelseaVSPort ValeRRƯỢU MẬNĐặt cược · 2 BLV",
                      "stream_links": [
                        {
                          "id": "qc-5-chelsea-vs-port-vale-lnk-0",
                          "name": "🎙 RƯỢU MẬN — Auto",
                          "type": "hls",
                          "default": true,
                          "url": "https://ahghndtkyqmm-pull.bpmedialive.com/quechoa/blv_6.m3u8",
                          "request_headers": [
                            {
                              "key": "Referer",
                              "value": "https://quechoa9.live/truc-tiep/chelsea-vs-port-vale-rrm-04-04-2026"
                            },
                            {
                              "key": "User-Agent",
                              "value": "Mozilla/5.0 (Windows NT 10.0; Win64; x64) AppleWebKit/537.36 (KHTML, like Gecko) Chrome/124.0.0.0 Safari/537.36"
                            }
                          ]
                        },
                        {
                          "id": "qc-5-chelsea-vs-port-vale-lnk-1",
                          "name": "🎙 RƯỢU MẬN — HD",
                          "type": "hls",
                          "default": false,
                          "url": "https://ahghndtkyqmm-pull.bpmedialive.com/quechoa/blv_6_hd.m3u8",
                          "request_headers": [
                            {
                              "key": "Referer",
                              "value": "https://quechoa9.live/truc-tiep/chelsea-vs-port-vale-rrm-04-04-2026"
                            },
                            {
                              "key": "User-Agent",
                              "value": "Mozilla/5.0 (Windows NT 10.0; Win64; x64) AppleWebKit/537.36 (KHTML, like Gecko) Chrome/124.0.0.0 Safari/537.36"
                            }
                          ]
                        },
                        {
                          "id": "qc-5-chelsea-vs-port-vale-lnk-2",
                          "name": "🎙 RƯỢU MẬN — SD",
                          "type": "hls",
                          "default": false,
                          "url": "https://ahghndtkyqmm-pull.bpmedialive.com/quechoa/blv_6_sd.m3u8",
                          "request_headers": [
                            {
                              "key": "Referer",
                              "value": "https://quechoa9.live/truc-tiep/chelsea-vs-port-vale-rrm-04-04-2026"
                            },
                            {
                              "key": "User-Agent",
                              "value": "Mozilla/5.0 (Windows NT 10.0; Win64; x64) AppleWebKit/537.36 (KHTML, like Gecko) Chrome/124.0.0.0 Safari/537.36"
                            }
                          ]
                        },
                        {
                          "id": "qc-5-chelsea-vs-port-vale-lnk-3",
                          "name": "🎙 NGƯỜI CHYM — Auto",
                          "type": "hls",
                          "default": false,
                          "url": "https://ahghndtkyqmm-pull.bpmedialive.com/quechoa/nhadai1.m3u8",
                          "request_headers": [
                            {
                              "key": "Referer",
                              "value": "https://quechoa9.live/truc-tiep/chelsea-vs-port-vale-hjm-04-04-2026"
                            },
                            {
                              "key": "User-Agent",
                              "value": "Mozilla/5.0 (Windows NT 10.0; Win64; x64) AppleWebKit/537.36 (KHTML, like Gecko) Chrome/124.0.0.0 Safari/537.36"
                            }
                          ]
                        },
                        {
                          "id": "qc-5-chelsea-vs-port-vale-lnk-4",
                          "name": "🎙 NGƯỜI CHYM — HD",
                          "type": "hls",
                          "default": false,
                          "url": "https://ahghndtkyqmm-pull.bpmedialive.com/quechoa/nhadai1_hd.m3u8",
                          "request_headers": [
                            {
                              "key": "Referer",
                              "value": "https://quechoa9.live/truc-tiep/chelsea-vs-port-vale-hjm-04-04-2026"
                            },
                            {
                              "key": "User-Agent",
                              "value": "Mozilla/5.0 (Windows NT 10.0; Win64; x64) AppleWebKit/537.36 (KHTML, like Gecko) Chrome/124.0.0.0 Safari/537.36"
                            }
                          ]
                        },
                        {
                          "id": "qc-5-chelsea-vs-port-vale-lnk-5",
                          "name": "🎙 NGƯỜI CHYM — SD",
                          "type": "hls",
                          "default": false,
                          "url": "https://ahghndtkyqmm-pull.bpmedialive.com/quechoa/nhadai1_sd.m3u8",
                          "request_headers": [
                            {
                              "key": "Referer",
                              "value": "https://quechoa9.live/truc-tiep/chelsea-vs-port-vale-hjm-04-04-2026"
                            },
                            {
                              "key": "User-Agent",
                              "value": "Mozilla/5.0 (Windows NT 10.0; Win64; x64) AppleWebKit/537.36 (KHTML, like Gecko) Chrome/124.0.0.0 Safari/537.36"
                            }
                          ]
                        }
                      ]
                    }
                  ]
                }
              ]
            }
          ]
        },
        {
          "id": "qc-6-southampton-vs-arsenal",
          "name": "Southampton vs Arsenal  🕐 19:00 | 04/04",
          "type": "single",
          "display": "thumbnail-only",
          "enable_detail": false,
          "image": {
            "padding": 1,
            "background_color": "#ececec",
            "display": "contain",
            "url": "https://quechoa9.live/images/cards/card-bg.jpg",
            "width": 1600,
            "height": 1200
          },
          "labels": [
            {
              "text": "🕐 Sắp diễn ra",
              "color": "#d54f1a",
              "text_color": "#ffffff",
              "position": "top-left"
            },
            {
              "text": "🎙 2 BLV",
              "position": "top-right",
              "color": "#00601f",
              "text_color": "#ffffff"
            },
            {
              "text": "🕐 19:00 | 04/04",
              "position": "bottom-left",
              "color": "#1a5fa8",
              "text_color": "#ffffff"
            }
          ],
          "sources": [
            {
              "id": "qc-6-southampton-vs-arsenal-src",
              "name": "QueCho9 Live",
              "contents": [
                {
                  "id": "qc-6-southampton-vs-arsenal-ct",
                  "name": "Southampton vs Arsenal  🕐 19:00 | 04/04",
                  "streams": [
                    {
                      "id": "qc-6-southampton-vs-arsenal-st",
                      "name": "Trực tiếp · Sắp diễn ra19:00|04.04FA CupSouthamptonVSArsenalDDƯA HẤUĐặt cược · 2 BLV",
                      "stream_links": [
                        {
                          "id": "qc-6-southampton-vs-arsenal-lnk-0",
                          "name": "🎙 DƯA HẤU — Full HD",
                          "type": "hls",
                          "default": true,
                          "url": "https://ahghndtkyqmm-pull.bpmedialive.com/quechoa/blv_supluon_full-hd.m3u8",
                          "request_headers": [
                            {
                              "key": "Referer",
                              "value": "https://quechoa9.live/truc-tiep/southampton-vs-arsenal-wlo-04-04-2026"
                            },
                            {
                              "key": "User-Agent",
                              "value": "Mozilla/5.0 (Windows NT 10.0; Win64; x64) AppleWebKit/537.36 (KHTML, like Gecko) Chrome/124.0.0.0 Safari/537.36"
                            }
                          ]
                        },
                        {
                          "id": "qc-6-southampton-vs-arsenal-lnk-1",
                          "name": "🎙 DƯA HẤU — HD",
                          "type": "hls",
                          "default": false,
                          "url": "https://ahghndtkyqmm-pull.bpmedialive.com/quechoa/blv_supluon_hd.m3u8",
                          "request_headers": [
                            {
                              "key": "Referer",
                              "value": "https://quechoa9.live/truc-tiep/southampton-vs-arsenal-wlo-04-04-2026"
                            },
                            {
                              "key": "User-Agent",
                              "value": "Mozilla/5.0 (Windows NT 10.0; Win64; x64) AppleWebKit/537.36 (KHTML, like Gecko) Chrome/124.0.0.0 Safari/537.36"
                            }
                          ]
                        },
                        {
                          "id": "qc-6-southampton-vs-arsenal-lnk-2",
                          "name": "🎙 DƯA HẤU — SD",
                          "type": "hls",
                          "default": false,
                          "url": "https://ahghndtkyqmm-pull.bpmedialive.com/quechoa/blv_supluon_sd.m3u8",
                          "request_headers": [
                            {
                              "key": "Referer",
                              "value": "https://quechoa9.live/truc-tiep/southampton-vs-arsenal-wlo-04-04-2026"
                            },
                            {
                              "key": "User-Agent",
                              "value": "Mozilla/5.0 (Windows NT 10.0; Win64; x64) AppleWebKit/537.36 (KHTML, like Gecko) Chrome/124.0.0.0 Safari/537.36"
                            }
                          ]
                        },
                        {
                          "id": "qc-6-southampton-vs-arsenal-lnk-3",
                          "name": "🎙 BÒ SỮA — Auto",
                          "type": "hls",
                          "default": false,
                          "url": "https://ahghndtkyqmm-pull.bpmedialive.com/quechoa/blv_5.m3u8",
                          "request_headers": [
                            {
                              "key": "Referer",
                              "value": "https://quechoa9.live/truc-tiep/southampton-vs-arsenal-pea-04-04-2026"
                            },
                            {
                              "key": "User-Agent",
                              "value": "Mozilla/5.0 (Windows NT 10.0; Win64; x64) AppleWebKit/537.36 (KHTML, like Gecko) Chrome/124.0.0.0 Safari/537.36"
                            }
                          ]
                        },
                        {
                          "id": "qc-6-southampton-vs-arsenal-lnk-4",
                          "name": "🎙 BÒ SỮA — HD",
                          "type": "hls",
                          "default": false,
                          "url": "https://ahghndtkyqmm-pull.bpmedialive.com/quechoa/blv_5_hd.m3u8",
                          "request_headers": [
                            {
                              "key": "Referer",
                              "value": "https://quechoa9.live/truc-tiep/southampton-vs-arsenal-pea-04-04-2026"
                            },
                            {
                              "key": "User-Agent",
                              "value": "Mozilla/5.0 (Windows NT 10.0; Win64; x64) AppleWebKit/537.36 (KHTML, like Gecko) Chrome/124.0.0.0 Safari/537.36"
                            }
                          ]
                        },
                        {
                          "id": "qc-6-southampton-vs-arsenal-lnk-5",
                          "name": "🎙 BÒ SỮA — SD",
                          "type": "hls",
                          "default": false,
                          "url": "https://ahghndtkyqmm-pull.bpmedialive.com/quechoa/blv_5_sd.m3u8",
                          "request_headers": [
                            {
                              "key": "Referer",
                              "value": "https://quechoa9.live/truc-tiep/southampton-vs-arsenal-pea-04-04-2026"
                            },
                            {
                              "key": "User-Agent",
                              "value": "Mozilla/5.0 (Windows NT 10.0; Win64; x64) AppleWebKit/537.36 (KHTML, like Gecko) Chrome/124.0.0.0 Safari/537.36"
                            }
                          ]
                        }
                      ]
                    }
                  ]
                }
              ]
            }
          ]
        },
        {
          "id": "qc-7-atletico-madrid-vs-barce",
          "name": "Atletico Madrid vs Barcelona  🕐 19:00 | 04/04",
          "type": "single",
          "display": "thumbnail-only",
          "enable_detail": false,
          "image": {
            "padding": 1,
            "background_color": "#ececec",
            "display": "contain",
            "url": "https://quechoa9.live/images/cards/card-bg.jpg",
            "width": 1600,
            "height": 1200
          },
          "labels": [
            {
              "text": "🕐 Sắp diễn ra",
              "color": "#d54f1a",
              "text_color": "#ffffff",
              "position": "top-left"
            },
            {
              "text": "🎙 2 BLV",
              "position": "top-right",
              "color": "#00601f",
              "text_color": "#ffffff"
            },
            {
              "text": "🕐 19:00 | 04/04",
              "position": "bottom-left",
              "color": "#1a5fa8",
              "text_color": "#ffffff"
            }
          ],
          "sources": [
            {
              "id": "qc-7-atletico-madrid-vs-barce-src",
              "name": "QueCho9 Live",
              "contents": [
                {
                  "id": "qc-7-atletico-madrid-vs-barce-ct",
                  "name": "Atletico Madrid vs Barcelona  🕐 19:00 | 04/04",
                  "streams": [
                    {
                      "id": "qc-7-atletico-madrid-vs-barce-st",
                      "name": "Trực tiếp · Sắp diễn ra19:00|04.04La LigaAtletico MadridVSBarcelonaRRƯỢU MẬNĐặt cược · 2 BLV",
                      "stream_links": [
                        {
                          "id": "qc-7-atletico-madrid-vs-barce-lnk-0",
                          "name": "🎙 RƯỢU MẬN — Auto",
                          "type": "hls",
                          "default": true,
                          "url": "https://ahghndtkyqmm-pull.bpmedialive.com/quechoa/blv_6.m3u8",
                          "request_headers": [
                            {
                              "key": "Referer",
                              "value": "https://quechoa9.live/truc-tiep/atletico-madrid-vs-barcelona-kxk-04-04-2026"
                            },
                            {
                              "key": "User-Agent",
                              "value": "Mozilla/5.0 (Windows NT 10.0; Win64; x64) AppleWebKit/537.36 (KHTML, like Gecko) Chrome/124.0.0.0 Safari/537.36"
                            }
                          ]
                        },
                        {
                          "id": "qc-7-atletico-madrid-vs-barce-lnk-1",
                          "name": "🎙 RƯỢU MẬN — HD",
                          "type": "hls",
                          "default": false,
                          "url": "https://ahghndtkyqmm-pull.bpmedialive.com/quechoa/blv_6_hd.m3u8",
                          "request_headers": [
                            {
                              "key": "Referer",
                              "value": "https://quechoa9.live/truc-tiep/atletico-madrid-vs-barcelona-kxk-04-04-2026"
                            },
                            {
                              "key": "User-Agent",
                              "value": "Mozilla/5.0 (Windows NT 10.0; Win64; x64) AppleWebKit/537.36 (KHTML, like Gecko) Chrome/124.0.0.0 Safari/537.36"
                            }
                          ]
                        },
                        {
                          "id": "qc-7-atletico-madrid-vs-barce-lnk-2",
                          "name": "🎙 RƯỢU MẬN — SD",
                          "type": "hls",
                          "default": false,
                          "url": "https://ahghndtkyqmm-pull.bpmedialive.com/quechoa/blv_6_sd.m3u8",
                          "request_headers": [
                            {
                              "key": "Referer",
                              "value": "https://quechoa9.live/truc-tiep/atletico-madrid-vs-barcelona-kxk-04-04-2026"
                            },
                            {
                              "key": "User-Agent",
                              "value": "Mozilla/5.0 (Windows NT 10.0; Win64; x64) AppleWebKit/537.36 (KHTML, like Gecko) Chrome/124.0.0.0 Safari/537.36"
                            }
                          ]
                        },
                        {
                          "id": "qc-7-atletico-madrid-vs-barce-lnk-3",
                          "name": "🎙 KHU MẤN",
                          "type": "hls",
                          "default": false,
                          "url": "https://ahghndtkyqmm-pull.bpmedialive.com/quechoa/blv_lachanh_full-hd.m3u8",
                          "request_headers": [
                            {
                              "key": "Referer",
                              "value": "https://quechoa9.live/truc-tiep/atletico-madrid-vs-barcelona-zfj-04-04-2026"
                            },
                            {
                              "key": "User-Agent",
                              "value": "Mozilla/5.0 (Windows NT 10.0; Win64; x64) AppleWebKit/537.36 (KHTML, like Gecko) Chrome/124.0.0.0 Safari/537.36"
                            }
                          ]
                        }
                      ]
                    }
                  ]
                }
              ]
            }
          ]
        }
      ]
    }
  ]
}